README.md
setup.py
kvrocket/__init__.py
kvrocket.egg-info/PKG-INFO
kvrocket.egg-info/SOURCES.txt
kvrocket.egg-info/dependency_links.txt
kvrocket.egg-info/requires.txt
kvrocket.egg-info/top_level.txt